Metadata-Version: 2.1
Name: tenai
Version: 1.1.1
Summary: Uncover part of the mutuals followers of an instagram private account
Home-page: https://github.com/novitae/Tenai
Author: novitae
License: GNU General Public License v3 (GPLv3)
Platform: UNKNOWN
Classifier: Programming Language :: Python :: 3.9
License-File: LICENCE
